LICENSE
setup.py
VioleRCNG.egg-info/PKG-INFO
VioleRCNG.egg-info/SOURCES.txt
VioleRCNG.egg-info/dependency_links.txt
VioleRCNG.egg-info/requires.txt
VioleRCNG.egg-info/top_level.txt
viole_rcng/__init__.py
viole_rcng/viole_rcng.py