Metadata-Version: 2.1
Name: VioleRCNG
Version: 0.0.1
Summary: A random code name generator for anything
Author: Jorge Magno
Author-email: jorge.estudos0@gmail.com
License: MIT License
Keywords: code,name generator
License-File: LICENSE
Requires-Dist: random
Requires-Dist: string
